setup.cfg
setup.py
XS_khtab/__init__.py
XS_khtab.egg-info/PKG-INFO
XS_khtab.egg-info/SOURCES.txt
XS_khtab.egg-info/dependency_links.txt
XS_khtab.egg-info/top_level.txt