Metadata-Version: 2.4
Name: XS_khtab
Version: 1.1
Summary: The Lib By Khtab In SxTeam
Author: XS_khtab
Classifier: Programming Language :: Python :: 3
Dynamic: author
Dynamic: classifier
Dynamic: summary
